wase_api/__init__.py
wase_api/actionbar.py
wase_api/auras.py
wase_api/bit.py
wase_api/combat.py
wase_api/cvars.py
wase_api/enum.py
wase_api/events.py
wase_api/frames.py
wase_api/globals.py
wase_api/group.py
wase_api/hooksecurefunc.py
wase_api/inventory.py
wase_api/macros.py
wase_api/map.py
wase_api/math.py
wase_api/misc.py
wase_api/secure.py
wase_api/spells.py
wase_api/targeting.py
wase_api/time.py
wase_api/unit.py
wase_api/update_loop.py
wase_api/widgets.py
wase_core/__init__.py
wase_core/engine.py
wase_core/icon_downloader.py
wase_core/spell_updater.py
wase_core/stubs.py
wase_data/__init__.py
wasengine-1.0.11.dist-info/licenses/LICENSE
wasengine-1.0.11.dist-info/METADATA
wasengine-1.0.11.dist-info/WHEEL
wasengine-1.0.11.dist-info/top_level.txt
wasengine-1.0.11.dist-info/RECORD
